INSTALL.txt
LICENSE.txt
MANIFEST.in
README.txt
distribute_setup.py
setup.cfg
setup.py
javasrc/Makefile
javasrc/README.txt
javasrc/org/nltk/mallet/CRFInfo.java
javasrc/org/nltk/mallet/RunCRF.java
javasrc/org/nltk/mallet/TrainCRF.java
nltk/VERSION
nltk/__init__.py
nltk/align.py
nltk/book.py
nltk/collocations.py
nltk/data.py
nltk/decorators.py
nltk/downloader.py
nltk/featstruct.py
nltk/grammar.py
nltk/help.py
nltk/internals.py
nltk/lazyimport.py
nltk/nltk.jar
nltk/probability.py
nltk/sourcedstring.py
nltk/text.py
nltk/toolbox.py
nltk/tree.py
nltk/treetransforms.py
nltk/util.py
nltk/yamltags.py
nltk/app/__init__.py
nltk/app/chartparser_app.py
nltk/app/chunkparser_app.py
nltk/app/collocations_app.py
nltk/app/concordance_app.py
nltk/app/nemo_app.py
nltk/app/rdparser_app.py
nltk/app/srparser_app.py
nltk/app/wordfreq_app.py
nltk/app/wordnet_app.py
nltk/ccg/__init__.py
nltk/ccg/api.py
nltk/ccg/chart.py
nltk/ccg/combinator.py
nltk/ccg/lexicon.py
nltk/chat/__init__.py
nltk/chat/eliza.py
nltk/chat/iesha.py
nltk/chat/rude.py
nltk/chat/suntsu.py
nltk/chat/util.py
nltk/chat/zen.py
nltk/chunk/__init__.py
nltk/chunk/api.py
nltk/chunk/named_entity.py
nltk/chunk/regexp.py
nltk/chunk/util.py
nltk/classify/__init__.py
nltk/classify/api.py
nltk/classify/decisiontree.py
nltk/classify/mallet.py
nltk/classify/maxent.py
nltk/classify/megam.py
nltk/classify/naivebayes.py
nltk/classify/positivenaivebayes.py
nltk/classify/rte_classify.py
nltk/classify/scikitlearn.py
nltk/classify/svm.py
nltk/classify/tadm.py
nltk/classify/util.py
nltk/classify/weka.py
nltk/cluster/__init__.py
nltk/cluster/api.py
nltk/cluster/em.py
nltk/cluster/gaac.py
nltk/cluster/kmeans.py
nltk/cluster/util.py
nltk/corpus/__init__.py
nltk/corpus/europarl_raw.py
nltk/corpus/util.py
nltk/corpus/reader/__init__.py
nltk/corpus/reader/aligned.py
nltk/corpus/reader/api.py
nltk/corpus/reader/bnc.py
nltk/corpus/reader/bracket_parse.py
nltk/corpus/reader/chasen.py
nltk/corpus/reader/childes.py
nltk/corpus/reader/chunked.py
nltk2_fixed.egg-info/PKG-INFO
nltk2_fixed.egg-info/SOURCES.txt
nltk2_fixed.egg-info/dependency_links.txt
nltk2_fixed.egg-info/not-zip-safe
nltk2_fixed.egg-info/requires.txt
nltk2_fixed.egg-info/top_level.txt